flask_keepincheck.py
Flask_Keepincheck-0.1.dist-info/LICENSE
Flask_Keepincheck-0.1.dist-info/METADATA
Flask_Keepincheck-0.1.dist-info/WHEEL
Flask_Keepincheck-0.1.dist-info/top_level.txt
Flask_Keepincheck-0.1.dist-info/RECORD
