Metadata-Version: 2.1
Name: Flask-Keepincheck
Version: 0.1
Summary: Healthchecks for upstream dependencies of a Flask app
Home-page: https://github.com/Shuttl-Tech/flask-keepincheck
Author: Abhirag Awasthi
Author-email: abhirag.awasthi@shuttl.com
License: MIT
Platform: any
Classifier: Environment :: Web Environment
Classifier: Intended Audience :: Developers
Classifier: License :: OSI Approved :: MIT License
Classifier: Operating System :: OS Independent
Classifier: Programming Language :: Python :: 3
Classifier: Topic :: Internet :: WWW/HTTP :: Dynamic Content
Classifier: Topic :: Software Development :: Libraries :: Python Modules
Requires-Dist: Flask
Requires-Dist: Flask-SQLAlchemy
